{
  "$schema": "https://fides.community/schemas/wallet-catalog/v1",
  "provider": {
    "name": "Validated ID",
    "website": "https://www.validatedid.com",
    "logo": "https://logo.clearbit.com/validatedid.com"
  },
  "wallets": [
    {
      "id": "vidwallet",
      "name": "VIDwallet",
      "logo": "https://play-lh.googleusercontent.com/jHhBYSsZ0gPRKmOVv0d5pT2L9B0Rb8hPWY8xZD4RTEuH8bLBVy8rYxVqG5b5qpj5qQ=w480-h960",
      "description": "A HAIP-compliant digital identity wallet enabling secure storage and presentation of verifiable credentials for individuals and organizations.",
      "type": "personal",
      "platforms": ["iOS", "Android"],
      "credentialFormats": ["SD-JWT-VC", "JWT-VC"],
      "protocols": {
        "issuance": ["OpenID4VCI"],
        "presentation": ["OpenID4VP"]
      },
      "interoperabilityProfiles": ["HAIP"],
      "website": "https://www.validatedid.com",
      "appStoreLinks": {
        "iOS": "https://apps.apple.com/app/vidwallet/id1554340592",
        "android": "https://play.google.com/store/apps/details?id=com.validatedid.wallet"
      },
      "openSource": false,
      "status": "production"
    }
  ],
  "lastUpdated": "2025-01-06T12:00:00Z"
}

