{
  "$schema": "https://fides.community/schemas/wallet-catalog/v1",
  "provider": {
    "name": "Procivis",
    "website": "https://www.procivis.ch",
    "logo": "https://www.google.com/s2/favicons?domain=procivis.ch&sz=128",
    "country": "CH"
  },
  "wallets": [
    {
      "id": "procivis-one",
      "name": "Procivis One",
      "description": "A Swiss enterprise identity platform providing issuer and verifier capabilities for verifiable credentials with a focus on privacy and compliance.",
      "logo": "https://www.google.com/s2/favicons?domain=procivis.ch&sz=128",
      "website": "https://www.procivis.ch",
      "type": "organizational",
      "capabilities": ["issuer", "verifier"],
      "platforms": ["Web"],
      "credentialFormats": ["SD-JWT-VC", "JWT-VC", "mDL/mDoc"],
      "issuanceProtocols": ["OpenID4VCI"],
      "presentationProtocols": ["OpenID4VP"],
      "openSource": false,
      "status": "production"
    }
  ],
  "lastUpdated": "2026-01-06T12:00:00Z"
}

